setup.py
django_unusual.egg-info/PKG-INFO
django_unusual.egg-info/SOURCES.txt
django_unusual.egg-info/dependency_links.txt
django_unusual.egg-info/requires.txt
django_unusual.egg-info/top_level.txt
unusual/__init__.py
unusual/http.py