Metadata-Version: 1.1
Name: django-unusual
Version: 0.1
Summary: Allows django apps to raise HttpResponse objects as exceptions.
Home-page: https://github.com/dvogel/django-unusual
Author: Drew Vogel
Author-email: drewpvogel@gmail.com
License: BSD
Platform: any
Classifier: Development Status :: 4 - Beta
Classifier: Intended Audience :: Developers
Classifier: License :: OSI Approved :: BSD License
Classifier: Natural Language :: English
Classifier: Operating System :: OS Independent
Classifier: Programming Language :: Python
Classifier: Topic :: Software Development :: Libraries :: Python Modules
